flask_escapejse.py
Flask_EscapeJSe-1.0.0.dist-info/LICENSE
Flask_EscapeJSe-1.0.0.dist-info/METADATA
Flask_EscapeJSe-1.0.0.dist-info/WHEEL
Flask_EscapeJSe-1.0.0.dist-info/top_level.txt
Flask_EscapeJSe-1.0.0.dist-info/RECORD
