Metadata-Version: 2.1
Name: Flask-EscapeJSe
Version: 1.0.0
Summary: Escape curly braces in jinja template for use in JS         frameworks
Home-page: https://github.com/akhilharihar/Flask-EscapeJSe
Author: Akhil Harihar
Author-email: hariharakhil@gmail.com
License: MIT
Platform: any
Classifier: Programming Language :: Python :: 3
Classifier: License :: OSI Approved :: MIT License
Classifier: Operating System :: OS Independent
Classifier: Framework :: Flask
Classifier: Intended Audience :: Developers
Classifier: Topic :: Software Development
Classifier: Development Status :: 5 - Production/Stable
Requires-Python: >=3.0
Requires-Dist: Flask
Requires-Dist: Jinja2
